trrex/__init__.py
trrex/trrex.py
trrex/benchmarks/find.py
trrex/benchmarks/pandas_contains.py
trrex/benchmarks/pandas_findall.py
trrex-0.0.6.dist-info/METADATA
trrex-0.0.6.dist-info/WHEEL
trrex-0.0.6.dist-info/licenses/LICENSE
trrex-0.0.6.dist-info/RECORD
