Metadata-Version: 2.4
Name: trrex
Version: 0.0.6
Summary: Transform set of words to efficient regular expression
Project-URL: Homepage, https://github.com/mesejo/trex
Author-email: Daniel Mesejo <mesejoleon@gmail.com>
License: LICENSE
License-File: LICENSE
Classifier: Development Status :: 4 - Beta
Classifier: Environment :: Console
Classifier: Intended Audience :: Developers
Classifier: Intended Audience :: Science/Research
Classifier: License :: OSI Approved :: MIT License
Classifier: Operating System :: POSIX :: Linux
Classifier: Programming Language :: Python :: 3
Classifier: Topic :: Scientific/Engineering
Requires-Python: >=3.10
Requires-Dist: pip>=24.3.1
Requires-Dist: pytest-cov>=6.0.0
